keitaropy/__init__.py
keitaropy/client.py
keitaropy/models.py
keitaropy/api/__init__.py
keitaropy/api/affnetworks.py
keitaropy/api/api.py
keitaropy/api/campaigns.py
keitaropy/api/groups.py
keitaropy/api/offers.py
keitaropy/api/sources.py
keitaropy/api/streams.py
keitaropy-0.1.1.dist-info/LICENSE
keitaropy-0.1.1.dist-info/METADATA
keitaropy-0.1.1.dist-info/WHEEL
keitaropy-0.1.1.dist-info/top_level.txt
keitaropy-0.1.1.dist-info/RECORD
