Metadata-Version: 2.1
Name: keitaropy
Version: 0.1.1
Summary: Simple and easy to use API wrapper library for Keitaro Admin API written in Python3 and requests
Home-page: https://github.com/Infvmous/keitaropy
Author: Alex M
Author-email: alexeyheather@gmail.com
License: UNKNOWN
Project-URL: Source Code, https://github.com/Infvmous/keitaropy/tree/master/keitaropy
Project-URL: Documentation, https://github.com/Infvmous/keitaropy/blob/master/README.md
Project-URL: Keitaro Admin API Documentation, https://admin-api.docs.keitaro.io/
Keywords: keitaro api requests api-wrapper api-client python python3 admin-api
Platform: UNKNOWN
Classifier: Programming Language :: Python :: 3
Classifier: License :: OSI Approved :: MIT License
Classifier: Operating System :: OS Independent
Requires-Python: >=3.8
Requires-Dist: requests
